[
    {
        "numero": "4170459",
        "resumo": "Data contábil não esta visível para liberar e faturar os recursos",
        "severidade": "2",
        "categoria": "Sistemas.Saúde e Odonto.Apollo.Contas Médicas.Indisponibilidade",
        "status": "Resolvido",
        "grupo_executor": "EQUIPE TCS - TI SAUDE/ODONTO/PORTOMED/FSI",
        "responsavel": "BRUNO CESAR DIAS",
        "violacao_projetada": "null",
        "violado": "Não",
        "localidade": "Porto Saúde - Matriz",
        "data_abertura": "20/04/2020 08:41:10",
        "ultima_atualizacao": "20/04/2020 09:46:40",
        "retorno_chamado": "null",
        "classificacao_final": "Dúvida/Informação",
        "data_resolucao": "20/04/2020 09:45:54",
        "descricao": "Data contábil não esta visível para liberar e faturar os recursos",
        "usuario_final_afetado": "LAURA DUNDER DA COSTA",
        "departamento": "PSA - GESTAO SERVICOS SAUDE E OCUPACIONAL - 010014630",
        "problema_vinculado": "null",
        "incidente_pai": "null",
        "causado_pela_rdm": "null",
        "origem": "PortoNet",
        "ticket_sis_ext": "null"
    },
    {
        "numero": "4170459",
        "resumo": "Data contábil não esta visível para liberar e faturar os recursos",
        "severidade": "2",
        "categoria": "Sistemas.Saúde e Odonto.Apollo.Contas Médicas.Indisponibilidade",
        "status": "Resolvido",
        "grupo_executor": "EQUIPE TCS - TI SAUDE/ODONTO/PORTOMED/FSI",
        "responsavel": "BRUNO CESAR DIAS",
        "violacao_projetada": "null",
        "violado": "Não",
        "localidade": "Porto Saúde - Matriz",
        "data_abertura": "20/04/2020 08:41:10",
        "ultima_atualizacao": "20/04/2020 09:46:40",
        "retorno_chamado": "null",
        "classificacao_final": "Dúvida/Informação",
        "data_resolucao": "20/04/2020 09:45:54",
        "descricao": "Data contábil não esta visível para liberar e faturar os recursos",
        "usuario_final_afetado": "LAURA DUNDER DA COSTA",
        "departamento": "PSA - GESTAO SERVICOS SAUDE E OCUPACIONAL - 010014630",
        "problema_vinculado": "null",
        "incidente_pai": "null",
        "causado_pela_rdm": "null",
        "origem": "PortoNet",
        "ticket_sis_ext": "null"
    },
    {
        "numero": "4170459",
        "resumo": "Data contábil não esta visível para liberar e faturar os recursos",
        "severidade": "2",
        "categoria": "Sistemas.Saúde e Odonto.Apollo.Contas Médicas.Indisponibilidade",
        "status": "Resolvido",
        "grupo_executor": "EQUIPE TCS - TI SAUDE/ODONTO/PORTOMED/FSI",
        "responsavel": "BRUNO CESAR DIAS",
        "violacao_projetada": "null",
        "violado": "Não",
        "localidade": "Porto Saúde - Matriz",
        "data_abertura": "20/04/2020 08:41:10",
        "ultima_atualizacao": "20/04/2020 09:46:40",
        "retorno_chamado": "null",
        "classificacao_final": "Dúvida/Informação",
        "data_resolucao": "20/04/2020 09:45:54",
        "descricao": "Data contábil não esta visível para liberar e faturar os recursos",
        "usuario_final_afetado": "LAURA DUNDER DA COSTA",
        "departamento": "PSA - GESTAO SERVICOS SAUDE E OCUPACIONAL - 010014630",
        "problema_vinculado": "null",
        "incidente_pai": "null",
        "causado_pela_rdm": "null",
        "origem": "PortoNet",
        "ticket_sis_ext": "null"
    },
    {
        "numero": "4170459",
        "resumo": "Data contábil não esta visível para liberar e faturar os recursos",
        "severidade": "2",
        "categoria": "Sistemas.Saúde e Odonto.Apollo.Contas Médicas.Indisponibilidade",
        "status": "Resolvido",
        "grupo_executor": "EQUIPE TCS - TI SAUDE/ODONTO/PORTOMED/FSI",
        "responsavel": "BRUNO CESAR DIAS",
        "violacao_projetada": "null",
        "violado": "Não",
        "localidade": "Porto Saúde - Matriz",
        "data_abertura": "20/04/2020 08:41:10",
        "ultima_atualizacao": "20/04/2020 09:46:40",
        "retorno_chamado": "null",
        "classificacao_final": "Dúvida/Informação",
        "data_resolucao": "20/04/2020 09:45:54",
        "descricao": "Data contábil não esta visível para liberar e faturar os recursos",
        "usuario_final_afetado": "LAURA DUNDER DA COSTA",
        "departamento": "PSA - GESTAO SERVICOS SAUDE E OCUPACIONAL - 010014630",
        "problema_vinculado": "null",
        "incidente_pai": "null",
        "causado_pela_rdm": "null",
        "origem": "PortoNet",
        "ticket_sis_ext": "null"
    },
    {
        "numero": "4170459",
        "resumo": "Data contábil não esta visível para liberar e faturar os recursos",
        "severidade": "2",
        "categoria": "Sistemas.Saúde e Odonto.Apollo.Contas Médicas.Indisponibilidade",
        "status": "Resolvido",
        "grupo_executor": "EQUIPE TCS - TI SAUDE/ODONTO/PORTOMED/FSI",
        "responsavel": "BRUNO CESAR DIAS",
        "violacao_projetada": "null",
        "violado": "Não",
        "localidade": "Porto Saúde - Matriz",
        "data_abertura": "20/04/2020 08:41:10",
        "ultima_atualizacao": "20/04/2020 09:46:40",
        "retorno_chamado": "null",
        "classificacao_final": "Dúvida/Informação",
        "data_resolucao": "20/04/2020 09:45:54",
        "descricao": "Data contábil não esta visível para liberar e faturar os recursos",
        "usuario_final_afetado": "LAURA DUNDER DA COSTA",
        "departamento": "PSA - GESTAO SERVICOS SAUDE E OCUPACIONAL - 010014630",
        "problema_vinculado": "null",
        "incidente_pai": "null",
        "causado_pela_rdm": "null",
        "origem": "PortoNet",
        "ticket_sis_ext": "null"
    },
    {
        "numero": "4170459",
        "resumo": "Data contábil não esta visível para liberar e faturar os recursos",
        "severidade": "2",
        "categoria": "Sistemas.Saúde e Odonto.Apollo.Contas Médicas.Indisponibilidade",
        "status": "Resolvido",
        "grupo_executor": "EQUIPE TCS - TI SAUDE/ODONTO/PORTOMED/FSI",
        "responsavel": "BRUNO CESAR DIAS",
        "violacao_projetada": "null",
        "violado": "Não",
        "localidade": "Porto Saúde - Matriz",
        "data_abertura": "20/04/2020 08:41:10",
        "ultima_atualizacao": "20/04/2020 09:46:40",
        "retorno_chamado": "null",
        "classificacao_final": "Dúvida/Informação",
        "data_resolucao": "20/04/2020 09:45:54",
        "descricao": "Data contábil não esta visível para liberar e faturar os recursos",
        "usuario_final_afetado": "LAURA DUNDER DA COSTA",
        "departamento": "PSA - GESTAO SERVICOS SAUDE E OCUPACIONAL - 010014630",
        "problema_vinculado": "null",
        "incidente_pai": "null",
        "causado_pela_rdm": "null",
        "origem": "PortoNet",
        "ticket_sis_ext": "null"
    },
    {
        "numero": "4170459",
        "resumo": "Data contábil não esta visível para liberar e faturar os recursos",
        "severidade": "2",
        "categoria": "Sistemas.Saúde e Odonto.Apollo.Contas Médicas.Indisponibilidade",
        "status": "Resolvido",
        "grupo_executor": "EQUIPE TCS - TI SAUDE/ODONTO/PORTOMED/FSI",
        "responsavel": "BRUNO CESAR DIAS",
        "violacao_projetada": "null",
        "violado": "Não",
        "localidade": "Porto Saúde - Matriz",
        "data_abertura": "20/04/2020 08:41:10",
        "ultima_atualizacao": "20/04/2020 09:46:40",
        "retorno_chamado": "null",
        "classificacao_final": "Dúvida/Informação",
        "data_resolucao": "20/04/2020 09:45:54",
        "descricao": "Data contábil não esta visível para liberar e faturar os recursos",
        "usuario_final_afetado": "LAURA DUNDER DA COSTA",
        "departamento": "PSA - GESTAO SERVICOS SAUDE E OCUPACIONAL - 010014630",
        "problema_vinculado": "null",
        "incidente_pai": "null",
        "causado_pela_rdm": "null",
        "origem": "PortoNet",
        "ticket_sis_ext": "null"
    },
    {
        "numero": "4170459",
        "resumo": "Data contábil não esta visível para liberar e faturar os recursos",
        "severidade": "2",
        "categoria": "Sistemas.Saúde e Odonto.Apollo.Contas Médicas.Indisponibilidade",
        "status": "Resolvido",
        "grupo_executor": "EQUIPE TCS - TI SAUDE/ODONTO/PORTOMED/FSI",
        "responsavel": "BRUNO CESAR DIAS",
        "violacao_projetada": "null",
        "violado": "Não",
        "localidade": "Porto Saúde - Matriz",
        "data_abertura": "20/04/2020 08:41:10",
        "ultima_atualizacao": "20/04/2020 09:46:40",
        "retorno_chamado": "null",
        "classificacao_final": "Dúvida/Informação",
        "data_resolucao": "20/04/2020 09:45:54",
        "descricao": "Data contábil não esta visível para liberar e faturar os recursos",
        "usuario_final_afetado": "LAURA DUNDER DA COSTA",
        "departamento": "PSA - GESTAO SERVICOS SAUDE E OCUPACIONAL - 010014630",
        "problema_vinculado": "null",
        "incidente_pai": "null",
        "causado_pela_rdm": "null",
        "origem": "PortoNet",
        "ticket_sis_ext": "null"
    },
    {
        "numero": "4170459",
        "resumo": "Data contábil não esta visível para liberar e faturar os recursos",
        "severidade": "2",
        "categoria": "Sistemas.Saúde e Odonto.Apollo.Contas Médicas.Indisponibilidade",
        "status": "Resolvido",
        "grupo_executor": "EQUIPE TCS - TI SAUDE/ODONTO/PORTOMED/FSI",
        "responsavel": "BRUNO CESAR DIAS",
        "violacao_projetada": "null",
        "violado": "Não",
        "localidade": "Porto Saúde - Matriz",
        "data_abertura": "20/04/2020 08:41:10",
        "ultima_atualizacao": "20/04/2020 09:46:40",
        "retorno_chamado": "null",
        "classificacao_final": "Dúvida/Informação",
        "data_resolucao": "20/04/2020 09:45:54",
        "descricao": "Data contábil não esta visível para liberar e faturar os recursos",
        "usuario_final_afetado": "LAURA DUNDER DA COSTA",
        "departamento": "PSA - GESTAO SERVICOS SAUDE E OCUPACIONAL - 010014630",
        "problema_vinculado": "null",
        "incidente_pai": "null",
        "causado_pela_rdm": "null",
        "origem": "PortoNet",
        "ticket_sis_ext": "null"
    },
    {
        "numero": "4170459",
        "resumo": "Data contábil não esta visível para liberar e faturar os recursos",
        "severidade": "2",
        "categoria": "Sistemas.Saúde e Odonto.Apollo.Contas Médicas.Indisponibilidade",
        "status": "Resolvido",
        "grupo_executor": "EQUIPE TCS - TI SAUDE/ODONTO/PORTOMED/FSI",
        "responsavel": "BRUNO CESAR DIAS",
        "violacao_projetada": "null",
        "violado": "Não",
        "localidade": "Porto Saúde - Matriz",
        "data_abertura": "20/04/2020 08:41:10",
        "ultima_atualizacao": "20/04/2020 09:46:40",
        "retorno_chamado": "null",
        "classificacao_final": "Dúvida/Informação",
        "data_resolucao": "20/04/2020 09:45:54",
        "descricao": "Data contábil não esta visível para liberar e faturar os recursos",
        "usuario_final_afetado": "LAURA DUNDER DA COSTA",
        "departamento": "PSA - GESTAO SERVICOS SAUDE E OCUPACIONAL - 010014630",
        "problema_vinculado": "null",
        "incidente_pai": "null",
        "causado_pela_rdm": "null",
        "origem": "PortoNet",
        "ticket_sis_ext": "null"
    },
    {
        "numero": "4170459",
        "resumo": "Data contábil não esta visível para liberar e faturar os recursos",
        "severidade": "2",
        "categoria": "Sistemas.Saúde e Odonto.Apollo.Contas Médicas.Indisponibilidade",
        "status": "Resolvido",
        "grupo_executor": "EQUIPE TCS - TI SAUDE/ODONTO/PORTOMED/FSI",
        "responsavel": "BRUNO CESAR DIAS",
        "violacao_projetada": "null",
        "violado": "Não",
        "localidade": "Porto Saúde - Matriz",
        "data_abertura": "20/04/2020 08:41:10",
        "ultima_atualizacao": "20/04/2020 09:46:40",
        "retorno_chamado": "null",
        "classificacao_final": "Dúvida/Informação",
        "data_resolucao": "20/04/2020 09:45:54",
        "descricao": "Data contábil não esta visível para liberar e faturar os recursos",
        "usuario_final_afetado": "LAURA DUNDER DA COSTA",
        "departamento": "PSA - GESTAO SERVICOS SAUDE E OCUPACIONAL - 010014630",
        "problema_vinculado": "null",
        "incidente_pai": "null",
        "causado_pela_rdm": "null",
        "origem": "PortoNet",
        "ticket_sis_ext": "null"
    },
    {
        "numero": "4170459",
        "resumo": "Data contábil não esta visível para liberar e faturar os recursos",
        "severidade": "2",
        "categoria": "Sistemas.Saúde e Odonto.Apollo.Contas Médicas.Indisponibilidade",
        "status": "Resolvido",
        "grupo_executor": "EQUIPE TCS - TI SAUDE/ODONTO/PORTOMED/FSI",
        "responsavel": "BRUNO CESAR DIAS",
        "violacao_projetada": "null",
        "violado": "Não",
        "localidade": "Porto Saúde - Matriz",
        "data_abertura": "20/04/2020 08:41:10",
        "ultima_atualizacao": "20/04/2020 09:46:40",
        "retorno_chamado": "null",
        "classificacao_final": "Dúvida/Informação",
        "data_resolucao": "20/04/2020 09:45:54",
        "descricao": "Data contábil não esta visível para liberar e faturar os recursos",
        "usuario_final_afetado": "LAURA DUNDER DA COSTA",
        "departamento": "PSA - GESTAO SERVICOS SAUDE E OCUPACIONAL - 010014630",
        "problema_vinculado": "null",
        "incidente_pai": "null",
        "causado_pela_rdm": "null",
        "origem": "PortoNet",
        "ticket_sis_ext": "null"
    },
    {
        "numero": "4170459",
        "resumo": "Data contábil não esta visível para liberar e faturar os recursos",
        "severidade": "2",
        "categoria": "Sistemas.Saúde e Odonto.Apollo.Contas Médicas.Indisponibilidade",
        "status": "Resolvido",
        "grupo_executor": "EQUIPE TCS - TI SAUDE/ODONTO/PORTOMED/FSI",
        "responsavel": "BRUNO CESAR DIAS",
        "violacao_projetada": "null",
        "violado": "Não",
        "localidade": "Porto Saúde - Matriz",
        "data_abertura": "20/04/2020 08:41:10",
        "ultima_atualizacao": "20/04/2020 09:46:40",
        "retorno_chamado": "null",
        "classificacao_final": "Dúvida/Informação",
        "data_resolucao": "20/04/2020 09:45:54",
        "descricao": "Data contábil não esta visível para liberar e faturar os recursos",
        "usuario_final_afetado": "LAURA DUNDER DA COSTA",
        "departamento": "PSA - GESTAO SERVICOS SAUDE E OCUPACIONAL - 010014630",
        "problema_vinculado": "null",
        "incidente_pai": "null",
        "causado_pela_rdm": "null",
        "origem": "PortoNet",
        "ticket_sis_ext": "null"
    },
    {
        "numero": "4170459",
        "resumo": "Data contábil não esta visível para liberar e faturar os recursos",
        "severidade": "2",
        "categoria": "Sistemas.Saúde e Odonto.Apollo.Contas Médicas.Indisponibilidade",
        "status": "Resolvido",
        "grupo_executor": "EQUIPE TCS - TI SAUDE/ODONTO/PORTOMED/FSI",
        "responsavel": "BRUNO CESAR DIAS",
        "violacao_projetada": "null",
        "violado": "Não",
        "localidade": "Porto Saúde - Matriz",
        "data_abertura": "20/04/2020 08:41:10",
        "ultima_atualizacao": "20/04/2020 09:46:40",
        "retorno_chamado": "null",
        "classificacao_final": "Dúvida/Informação",
        "data_resolucao": "20/04/2020 09:45:54",
        "descricao": "Data contábil não esta visível para liberar e faturar os recursos",
        "usuario_final_afetado": "LAURA DUNDER DA COSTA",
        "departamento": "PSA - GESTAO SERVICOS SAUDE E OCUPACIONAL - 010014630",
        "problema_vinculado": "null",
        "incidente_pai": "null",
        "causado_pela_rdm": "null",
        "origem": "PortoNet",
        "ticket_sis_ext": "null"
    },
    {
        "numero": "4170459",
        "resumo": "Data contábil não esta visível para liberar e faturar os recursos",
        "severidade": "2",
        "categoria": "Sistemas.Saúde e Odonto.Apollo.Contas Médicas.Indisponibilidade",
        "status": "Resolvido",
        "grupo_executor": "EQUIPE TCS - TI SAUDE/ODONTO/PORTOMED/FSI",
        "responsavel": "BRUNO CESAR DIAS",
        "violacao_projetada": "null",
        "violado": "Não",
        "localidade": "Porto Saúde - Matriz",
        "data_abertura": "20/04/2020 08:41:10",
        "ultima_atualizacao": "20/04/2020 09:46:40",
        "retorno_chamado": "null",
        "classificacao_final": "Dúvida/Informação",
        "data_resolucao": "20/04/2020 09:45:54",
        "descricao": "Data contábil não esta visível para liberar e faturar os recursos",
        "usuario_final_afetado": "LAURA DUNDER DA COSTA",
        "departamento": "PSA - GESTAO SERVICOS SAUDE E OCUPACIONAL - 010014630",
        "problema_vinculado": "null",
        "incidente_pai": "null",
        "causado_pela_rdm": "null",
        "origem": "PortoNet",
        "ticket_sis_ext": "null"
    },
    {
        "numero": "4170459",
        "resumo": "Data contábil não esta visível para liberar e faturar os recursos",
        "severidade": "2",
        "categoria": "Sistemas.Saúde e Odonto.Apollo.Contas Médicas.Indisponibilidade",
        "status": "Resolvido",
        "grupo_executor": "EQUIPE TCS - TI SAUDE/ODONTO/PORTOMED/FSI",
        "responsavel": "BRUNO CESAR DIAS",
        "violacao_projetada": "null",
        "violado": "Não",
        "localidade": "Porto Saúde - Matriz",
        "data_abertura": "20/04/2020 08:41:10",
        "ultima_atualizacao": "20/04/2020 09:46:40",
        "retorno_chamado": "null",
        "classificacao_final": "Dúvida/Informação",
        "data_resolucao": "20/04/2020 09:45:54",
        "descricao": "Data contábil não esta visível para liberar e faturar os recursos",
        "usuario_final_afetado": "LAURA DUNDER DA COSTA",
        "departamento": "PSA - GESTAO SERVICOS SAUDE E OCUPACIONAL - 010014630",
        "problema_vinculado": "null",
        "incidente_pai": "null",
        "causado_pela_rdm": "null",
        "origem": "PortoNet",
        "ticket_sis_ext": "null"
    },
    {
        "numero": "4170459",
        "resumo": "Data contábil não esta visível para liberar e faturar os recursos",
        "severidade": "2",
        "categoria": "Sistemas.Saúde e Odonto.Apollo.Contas Médicas.Indisponibilidade",
        "status": "Resolvido",
        "grupo_executor": "EQUIPE TCS - TI SAUDE/ODONTO/PORTOMED/FSI",
        "responsavel": "BRUNO CESAR DIAS",
        "violacao_projetada": "null",
        "violado": "Não",
        "localidade": "Porto Saúde - Matriz",
        "data_abertura": "20/04/2020 08:41:10",
        "ultima_atualizacao": "20/04/2020 09:46:40",
        "retorno_chamado": "null",
        "classificacao_final": "Dúvida/Informação",
        "data_resolucao": "20/04/2020 09:45:54",
        "descricao": "Data contábil não esta visível para liberar e faturar os recursos",
        "usuario_final_afetado": "LAURA DUNDER DA COSTA",
        "departamento": "PSA - GESTAO SERVICOS SAUDE E OCUPACIONAL - 010014630",
        "problema_vinculado": "null",
        "incidente_pai": "null",
        "causado_pela_rdm": "null",
        "origem": "PortoNet",
        "ticket_sis_ext": "null"
    },
    {
        "numero": "4170459",
        "resumo": "Data contábil não esta visível para liberar e faturar os recursos",
        "severidade": "2",
        "categoria": "Sistemas.Saúde e Odonto.Apollo.Contas Médicas.Indisponibilidade",
        "status": "Resolvido",
        "grupo_executor": "EQUIPE TCS - TI SAUDE/ODONTO/PORTOMED/FSI",
        "responsavel": "BRUNO CESAR DIAS",
        "violacao_projetada": "null",
        "violado": "Não",
        "localidade": "Porto Saúde - Matriz",
        "data_abertura": "20/04/2020 08:41:10",
        "ultima_atualizacao": "20/04/2020 09:46:40",
        "retorno_chamado": "null",
        "classificacao_final": "Dúvida/Informação",
        "data_resolucao": "20/04/2020 09:45:54",
        "descricao": "Data contábil não esta visível para liberar e faturar os recursos",
        "usuario_final_afetado": "LAURA DUNDER DA COSTA",
        "departamento": "PSA - GESTAO SERVICOS SAUDE E OCUPACIONAL - 010014630",
        "problema_vinculado": "null",
        "incidente_pai": "null",
        "causado_pela_rdm": "null",
        "origem": "PortoNet",
        "ticket_sis_ext": "null"
    },
    {
        "numero": "4170459",
        "resumo": "Data contábil não esta visível para liberar e faturar os recursos",
        "severidade": "2",
        "categoria": "Sistemas.Saúde e Odonto.Apollo.Contas Médicas.Indisponibilidade",
        "status": "Resolvido",
        "grupo_executor": "EQUIPE TCS - TI SAUDE/ODONTO/PORTOMED/FSI",
        "responsavel": "BRUNO CESAR DIAS",
        "violacao_projetada": "null",
        "violado": "Não",
        "localidade": "Porto Saúde - Matriz",
        "data_abertura": "20/04/2020 08:41:10",
        "ultima_atualizacao": "20/04/2020 09:46:40",
        "retorno_chamado": "null",
        "classificacao_final": "Dúvida/Informação",
        "data_resolucao": "20/04/2020 09:45:54",
        "descricao": "Data contábil não esta visível para liberar e faturar os recursos",
        "usuario_final_afetado": "LAURA DUNDER DA COSTA",
        "departamento": "PSA - GESTAO SERVICOS SAUDE E OCUPACIONAL - 010014630",
        "problema_vinculado": "null",
        "incidente_pai": "null",
        "causado_pela_rdm": "null",
        "origem": "PortoNet",
        "ticket_sis_ext": "null"
    },
    {
        "numero": "4170459",
        "resumo": "Data contábil não esta visível para liberar e faturar os recursos",
        "severidade": "2",
        "categoria": "Sistemas.Saúde e Odonto.Apollo.Contas Médicas.Indisponibilidade",
        "status": "Resolvido",
        "grupo_executor": "EQUIPE TCS - TI SAUDE/ODONTO/PORTOMED/FSI",
        "responsavel": "BRUNO CESAR DIAS",
        "violacao_projetada": "null",
        "violado": "Não",
        "localidade": "Porto Saúde - Matriz",
        "data_abertura": "20/04/2020 08:41:10",
        "ultima_atualizacao": "20/04/2020 09:46:40",
        "retorno_chamado": "null",
        "classificacao_final": "Dúvida/Informação",
        "data_resolucao": "20/04/2020 09:45:54",
        "descricao": "Data contábil não esta visível para liberar e faturar os recursos",
        "usuario_final_afetado": "LAURA DUNDER DA COSTA",
        "departamento": "PSA - GESTAO SERVICOS SAUDE E OCUPACIONAL - 010014630",
        "problema_vinculado": "null",
        "incidente_pai": "null",
        "causado_pela_rdm": "null",
        "origem": "PortoNet",
        "ticket_sis_ext": "null"
    },
    {
        "numero": "4170459",
        "resumo": "Data contábil não esta visível para liberar e faturar os recursos",
        "severidade": "2",
        "categoria": "Sistemas.Saúde e Odonto.Apollo.Contas Médicas.Indisponibilidade",
        "status": "Resolvido",
        "grupo_executor": "EQUIPE TCS - TI SAUDE/ODONTO/PORTOMED/FSI",
        "responsavel": "BRUNO CESAR DIAS",
        "violacao_projetada": "null",
        "violado": "Não",
        "localidade": "Porto Saúde - Matriz",
        "data_abertura": "20/04/2020 08:41:10",
        "ultima_atualizacao": "20/04/2020 09:46:40",
        "retorno_chamado": "null",
        "classificacao_final": "Dúvida/Informação",
        "data_resolucao": "20/04/2020 09:45:54",
        "descricao": "Data contábil não esta visível para liberar e faturar os recursos",
        "usuario_final_afetado": "LAURA DUNDER DA COSTA",
        "departamento": "PSA - GESTAO SERVICOS SAUDE E OCUPACIONAL - 010014630",
        "problema_vinculado": "null",
        "incidente_pai": "null",
        "causado_pela_rdm": "null",
        "origem": "PortoNet",
        "ticket_sis_ext": "null"
    },
    {
        "numero": "4170459",
        "resumo": "Data contábil não esta visível para liberar e faturar os recursos",
        "severidade": "2",
        "categoria": "Sistemas.Saúde e Odonto.Apollo.Contas Médicas.Indisponibilidade",
        "status": "Resolvido",
        "grupo_executor": "EQUIPE TCS - TI SAUDE/ODONTO/PORTOMED/FSI",
        "responsavel": "BRUNO CESAR DIAS",
        "violacao_projetada": "null",
        "violado": "Não",
        "localidade": "Porto Saúde - Matriz",
        "data_abertura": "20/04/2020 08:41:10",
        "ultima_atualizacao": "20/04/2020 09:46:40",
        "retorno_chamado": "null",
        "classificacao_final": "Dúvida/Informação",
        "data_resolucao": "20/04/2020 09:45:54",
        "descricao": "Data contábil não esta visível para liberar e faturar os recursos",
        "usuario_final_afetado": "LAURA DUNDER DA COSTA",
        "departamento": "PSA - GESTAO SERVICOS SAUDE E OCUPACIONAL - 010014630",
        "problema_vinculado": "null",
        "incidente_pai": "null",
        "causado_pela_rdm": "null",
        "origem": "PortoNet",
        "ticket_sis_ext": "null"
    },
    {
        "numero": "4170459",
        "resumo": "Data contábil não esta visível para liberar e faturar os recursos",
        "severidade": "2",
        "categoria": "Sistemas.Saúde e Odonto.Apollo.Contas Médicas.Indisponibilidade",
        "status": "Resolvido",
        "grupo_executor": "EQUIPE TCS - TI SAUDE/ODONTO/PORTOMED/FSI",
        "responsavel": "BRUNO CESAR DIAS",
        "violacao_projetada": "null",
        "violado": "Não",
        "localidade": "Porto Saúde - Matriz",
        "data_abertura": "20/04/2020 08:41:10",
        "ultima_atualizacao": "20/04/2020 09:46:40",
        "retorno_chamado": "null",
        "classificacao_final": "Dúvida/Informação",
        "data_resolucao": "20/04/2020 09:45:54",
        "descricao": "Data contábil não esta visível para liberar e faturar os recursos",
        "usuario_final_afetado": "LAURA DUNDER DA COSTA",
        "departamento": "PSA - GESTAO SERVICOS SAUDE E OCUPACIONAL - 010014630",
        "problema_vinculado": "null",
        "incidente_pai": "null",
        "causado_pela_rdm": "null",
        "origem": "PortoNet",
        "ticket_sis_ext": "null"
    },
    {
        "numero": "4170459",
        "resumo": "Data contábil não esta visível para liberar e faturar os recursos",
        "severidade": "2",
        "categoria": "Sistemas.Saúde e Odonto.Apollo.Contas Médicas.Indisponibilidade",
        "status": "Resolvido",
        "grupo_executor": "EQUIPE TCS - TI SAUDE/ODONTO/PORTOMED/FSI",
        "responsavel": "BRUNO CESAR DIAS",
        "violacao_projetada": "null",
        "violado": "Não",
        "localidade": "Porto Saúde - Matriz",
        "data_abertura": "20/04/2020 08:41:10",
        "ultima_atualizacao": "20/04/2020 09:46:40",
        "retorno_chamado": "null",
        "classificacao_final": "Dúvida/Informação",
        "data_resolucao": "20/04/2020 09:45:54",
        "descricao": "Data contábil não esta visível para liberar e faturar os recursos",
        "usuario_final_afetado": "LAURA DUNDER DA COSTA",
        "departamento": "PSA - GESTAO SERVICOS SAUDE E OCUPACIONAL - 010014630",
        "problema_vinculado": "null",
        "incidente_pai": "null",
        "causado_pela_rdm": "null",
        "origem": "PortoNet",
        "ticket_sis_ext": "null"
    },
    {
        "numero": "4170459",
        "resumo": "Data contábil não esta visível para liberar e faturar os recursos",
        "severidade": "2",
        "categoria": "Sistemas.Saúde e Odonto.Apollo.Contas Médicas.Indisponibilidade",
        "status": "Resolvido",
        "grupo_executor": "EQUIPE TCS - TI SAUDE/ODONTO/PORTOMED/FSI",
        "responsavel": "BRUNO CESAR DIAS",
        "violacao_projetada": "null",
        "violado": "Não",
        "localidade": "Porto Saúde - Matriz",
        "data_abertura": "20/04/2020 08:41:10",
        "ultima_atualizacao": "20/04/2020 09:46:40",
        "retorno_chamado": "null",
        "classificacao_final": "Dúvida/Informação",
        "data_resolucao": "20/04/2020 09:45:54",
        "descricao": "Data contábil não esta visível para liberar e faturar os recursos",
        "usuario_final_afetado": "LAURA DUNDER DA COSTA",
        "departamento": "PSA - GESTAO SERVICOS SAUDE E OCUPACIONAL - 010014630",
        "problema_vinculado": "null",
        "incidente_pai": "null",
        "causado_pela_rdm": "null",
        "origem": "PortoNet",
        "ticket_sis_ext": "null"
    },
    {
        "numero": "4165687",
        "resumo": "FAILED na aplicacao SAUDE_CARTAO_DAILY_17 job DNET_502_SOLICITACAO_CENTRAL_ITAU qualifier 0001 geracao 1256",
        "severidade": "2",
        "categoria": "Sistemas.Batch.Saude.Normal",
        "status": "Resolvido",
        "grupo_executor": "EQUIPE TCS - TI SAUDE/ODONTO/PORTOMED/FSI",
        "responsavel": "LEANDRO CAETANO DA SILVA",
        "violacao_projetada": "null",
        "violado": "Não",
        "localidade": "DATACENTER - 3º",
        "data_abertura": "16/04/2020 20:01:51",
        "ultima_atualizacao": "17/04/2020 23:31:01",
        "retorno_chamado": "null",
        "classificacao_final": "Incidente",
        "data_resolucao": "17/04/2020 23:30:31",
        "descricao": "Tipo de Desvio: FAILED Aplicacao: SAUDE_CARTAO_DAILY_17 Jobname: DNET_502_SOLICITACAO_CENTRAL_ITAU Qualifier: 0001 Geracao: 1256 Servidor: NT1044 Data: 16/04/2020 19:58:39 ----------------------------------------------- Quantidade de eventos de no mes: 2 (criado a partir da solicitação 4165694)",
        "usuario_final_afetado": "CAWA",
        "departamento": "PSG - PRODUCAO TI",
        "problema_vinculado": "null",
        "incidente_pai": "4165694",
        "causado_pela_rdm": "null",
        "origem": "PortoNet",
        "ticket_sis_ext": "null"
    },
    {
        "numero": "4165687",
        "resumo": "FAILED na aplicacao SAUDE_CARTAO_DAILY_17 job DNET_502_SOLICITACAO_CENTRAL_ITAU qualifier 0001 geracao 1256",
        "severidade": "2",
        "categoria": "Sistemas.Batch.Saude.Normal",
        "status": "Resolvido",
        "grupo_executor": "EQUIPE TCS - TI SAUDE/ODONTO/PORTOMED/FSI",
        "responsavel": "LEANDRO CAETANO DA SILVA",
        "violacao_projetada": "null",
        "violado": "Não",
        "localidade": "DATACENTER - 3º",
        "data_abertura": "16/04/2020 20:01:51",
        "ultima_atualizacao": "17/04/2020 23:31:01",
        "retorno_chamado": "null",
        "classificacao_final": "Incidente",
        "data_resolucao": "17/04/2020 23:30:31",
        "descricao": "Tipo de Desvio: FAILED Aplicacao: SAUDE_CARTAO_DAILY_17 Jobname: DNET_502_SOLICITACAO_CENTRAL_ITAU Qualifier: 0001 Geracao: 1256 Servidor: NT1044 Data: 16/04/2020 19:58:39 ----------------------------------------------- Quantidade de eventos de no mes: 2 (criado a partir da solicitação 4165694)",
        "usuario_final_afetado": "CAWA",
        "departamento": "PSG - PRODUCAO TI",
        "problema_vinculado": "null",
        "incidente_pai": "4165694",
        "causado_pela_rdm": "null",
        "origem": "PortoNet",
        "ticket_sis_ext": "null"
    },
    {
        "numero": "4165687",
        "resumo": "FAILED na aplicacao SAUDE_CARTAO_DAILY_17 job DNET_502_SOLICITACAO_CENTRAL_ITAU qualifier 0001 geracao 1256",
        "severidade": "2",
        "categoria": "Sistemas.Batch.Saude.Normal",
        "status": "Resolvido",
        "grupo_executor": "EQUIPE TCS - TI SAUDE/ODONTO/PORTOMED/FSI",
        "responsavel": "LEANDRO CAETANO DA SILVA",
        "violacao_projetada": "null",
        "violado": "Não",
        "localidade": "DATACENTER - 3º",
        "data_abertura": "16/04/2020 20:01:51",
        "ultima_atualizacao": "17/04/2020 23:31:01",
        "retorno_chamado": "null",
        "classificacao_final": "Incidente",
        "data_resolucao": "17/04/2020 23:30:31",
        "descricao": "Tipo de Desvio: FAILED Aplicacao: SAUDE_CARTAO_DAILY_17 Jobname: DNET_502_SOLICITACAO_CENTRAL_ITAU Qualifier: 0001 Geracao: 1256 Servidor: NT1044 Data: 16/04/2020 19:58:39 ----------------------------------------------- Quantidade de eventos de no mes: 2 (criado a partir da solicitação 4165694)",
        "usuario_final_afetado": "CAWA",
        "departamento": "PSG - PRODUCAO TI",
        "problema_vinculado": "null",
        "incidente_pai": "4165694",
        "causado_pela_rdm": "null",
        "origem": "PortoNet",
        "ticket_sis_ext": "null"
    },
    {
        "numero": "4165687",
        "resumo": "FAILED na aplicacao SAUDE_CARTAO_DAILY_17 job DNET_502_SOLICITACAO_CENTRAL_ITAU qualifier 0001 geracao 1256",
        "severidade": "2",
        "categoria": "Sistemas.Batch.Saude.Normal",
        "status": "Resolvido",
        "grupo_executor": "EQUIPE TCS - TI SAUDE/ODONTO/PORTOMED/FSI",
        "responsavel": "LEANDRO CAETANO DA SILVA",
        "violacao_projetada": "null",
        "violado": "Não",
        "localidade": "DATACENTER - 3º",
        "data_abertura": "16/04/2020 20:01:51",
        "ultima_atualizacao": "17/04/2020 23:31:01",
        "retorno_chamado": "null",
        "classificacao_final": "Incidente",
        "data_resolucao": "17/04/2020 23:30:31",
        "descricao": "Tipo de Desvio: FAILED Aplicacao: SAUDE_CARTAO_DAILY_17 Jobname: DNET_502_SOLICITACAO_CENTRAL_ITAU Qualifier: 0001 Geracao: 1256 Servidor: NT1044 Data: 16/04/2020 19:58:39 ----------------------------------------------- Quantidade de eventos de no mes: 2 (criado a partir da solicitação 4165694)",
        "usuario_final_afetado": "CAWA",
        "departamento": "PSG - PRODUCAO TI",
        "problema_vinculado": "null",
        "incidente_pai": "4165694",
        "causado_pela_rdm": "null",
        "origem": "PortoNet",
        "ticket_sis_ext": "null"
    },
    {
        "numero": "4165687",
        "resumo": "FAILED na aplicacao SAUDE_CARTAO_DAILY_17 job DNET_502_SOLICITACAO_CENTRAL_ITAU qualifier 0001 geracao 1256",
        "severidade": "2",
        "categoria": "Sistemas.Batch.Saude.Normal",
        "status": "Resolvido",
        "grupo_executor": "EQUIPE TCS - TI SAUDE/ODONTO/PORTOMED/FSI",
        "responsavel": "LEANDRO CAETANO DA SILVA",
        "violacao_projetada": "null",
        "violado": "Não",
        "localidade": "DATACENTER - 3º",
        "data_abertura": "16/04/2020 20:01:51",
        "ultima_atualizacao": "17/04/2020 23:31:01",
        "retorno_chamado": "null",
        "classificacao_final": "Incidente",
        "data_resolucao": "17/04/2020 23:30:31",
        "descricao": "Tipo de Desvio: FAILED Aplicacao: SAUDE_CARTAO_DAILY_17 Jobname: DNET_502_SOLICITACAO_CENTRAL_ITAU Qualifier: 0001 Geracao: 1256 Servidor: NT1044 Data: 16/04/2020 19:58:39 ----------------------------------------------- Quantidade de eventos de no mes: 2 (criado a partir da solicitação 4165694)",
        "usuario_final_afetado": "CAWA",
        "departamento": "PSG - PRODUCAO TI",
        "problema_vinculado": "null",
        "incidente_pai": "4165694",
        "causado_pela_rdm": "null",
        "origem": "PortoNet",
        "ticket_sis_ext": "null"
    },
    {
        "numero": "4165687",
        "resumo": "FAILED na aplicacao SAUDE_CARTAO_DAILY_17 job DNET_502_SOLICITACAO_CENTRAL_ITAU qualifier 0001 geracao 1256",
        "severidade": "2",
        "categoria": "Sistemas.Batch.Saude.Normal",
        "status": "Resolvido",
        "grupo_executor": "EQUIPE TCS - TI SAUDE/ODONTO/PORTOMED/FSI",
        "responsavel": "LEANDRO CAETANO DA SILVA",
        "violacao_projetada": "null",
        "violado": "Não",
        "localidade": "DATACENTER - 3º",
        "data_abertura": "16/04/2020 20:01:51",
        "ultima_atualizacao": "17/04/2020 23:31:01",
        "retorno_chamado": "null",
        "classificacao_final": "Incidente",
        "data_resolucao": "17/04/2020 23:30:31",
        "descricao": "Tipo de Desvio: FAILED Aplicacao: SAUDE_CARTAO_DAILY_17 Jobname: DNET_502_SOLICITACAO_CENTRAL_ITAU Qualifier: 0001 Geracao: 1256 Servidor: NT1044 Data: 16/04/2020 19:58:39 ----------------------------------------------- Quantidade de eventos de no mes: 2 (criado a partir da solicitação 4165694)",
        "usuario_final_afetado": "CAWA",
        "departamento": "PSG - PRODUCAO TI",
        "problema_vinculado": "null",
        "incidente_pai": "4165694",
        "causado_pela_rdm": "null",
        "origem": "PortoNet",
        "ticket_sis_ext": "null"
    },
    {
        "numero": "4165687",
        "resumo": "FAILED na aplicacao SAUDE_CARTAO_DAILY_17 job DNET_502_SOLICITACAO_CENTRAL_ITAU qualifier 0001 geracao 1256",
        "severidade": "2",
        "categoria": "Sistemas.Batch.Saude.Normal",
        "status": "Resolvido",
        "grupo_executor": "EQUIPE TCS - TI SAUDE/ODONTO/PORTOMED/FSI",
        "responsavel": "LEANDRO CAETANO DA SILVA",
        "violacao_projetada": "null",
        "violado": "Não",
        "localidade": "DATACENTER - 3º",
        "data_abertura": "16/04/2020 20:01:51",
        "ultima_atualizacao": "17/04/2020 23:31:01",
        "retorno_chamado": "null",
        "classificacao_final": "Incidente",
        "data_resolucao": "17/04/2020 23:30:31",
        "descricao": "Tipo de Desvio: FAILED Aplicacao: SAUDE_CARTAO_DAILY_17 Jobname: DNET_502_SOLICITACAO_CENTRAL_ITAU Qualifier: 0001 Geracao: 1256 Servidor: NT1044 Data: 16/04/2020 19:58:39 ----------------------------------------------- Quantidade de eventos de no mes: 2 (criado a partir da solicitação 4165694)",
        "usuario_final_afetado": "CAWA",
        "departamento": "PSG - PRODUCAO TI",
        "problema_vinculado": "null",
        "incidente_pai": "4165694",
        "causado_pela_rdm": "null",
        "origem": "PortoNet",
        "ticket_sis_ext": "null"
    },
    {
        "numero": "4165687",
        "resumo": "FAILED na aplicacao SAUDE_CARTAO_DAILY_17 job DNET_502_SOLICITACAO_CENTRAL_ITAU qualifier 0001 geracao 1256",
        "severidade": "2",
        "categoria": "Sistemas.Batch.Saude.Normal",
        "status": "Resolvido",
        "grupo_executor": "EQUIPE TCS - TI SAUDE/ODONTO/PORTOMED/FSI",
        "responsavel": "LEANDRO CAETANO DA SILVA",
        "violacao_projetada": "null",
        "violado": "Não",
        "localidade": "DATACENTER - 3º",
        "data_abertura": "16/04/2020 20:01:51",
        "ultima_atualizacao": "17/04/2020 23:31:01",
        "retorno_chamado": "null",
        "classificacao_final": "Incidente",
        "data_resolucao": "17/04/2020 23:30:31",
        "descricao": "Tipo de Desvio: FAILED Aplicacao: SAUDE_CARTAO_DAILY_17 Jobname: DNET_502_SOLICITACAO_CENTRAL_ITAU Qualifier: 0001 Geracao: 1256 Servidor: NT1044 Data: 16/04/2020 19:58:39 ----------------------------------------------- Quantidade de eventos de no mes: 2 (criado a partir da solicitação 4165694)",
        "usuario_final_afetado": "CAWA",
        "departamento": "PSG - PRODUCAO TI",
        "problema_vinculado": "null",
        "incidente_pai": "4165694",
        "causado_pela_rdm": "null",
        "origem": "PortoNet",
        "ticket_sis_ext": "null"
    },
    {
        "numero": "4165687",
        "resumo": "FAILED na aplicacao SAUDE_CARTAO_DAILY_17 job DNET_502_SOLICITACAO_CENTRAL_ITAU qualifier 0001 geracao 1256",
        "severidade": "2",
        "categoria": "Sistemas.Batch.Saude.Normal",
        "status": "Resolvido",
        "grupo_executor": "EQUIPE TCS - TI SAUDE/ODONTO/PORTOMED/FSI",
        "responsavel": "LEANDRO CAETANO DA SILVA",
        "violacao_projetada": "null",
        "violado": "Não",
        "localidade": "DATACENTER - 3º",
        "data_abertura": "16/04/2020 20:01:51",
        "ultima_atualizacao": "17/04/2020 23:31:01",
        "retorno_chamado": "null",
        "classificacao_final": "Incidente",
        "data_resolucao": "17/04/2020 23:30:31",
        "descricao": "Tipo de Desvio: FAILED Aplicacao: SAUDE_CARTAO_DAILY_17 Jobname: DNET_502_SOLICITACAO_CENTRAL_ITAU Qualifier: 0001 Geracao: 1256 Servidor: NT1044 Data: 16/04/2020 19:58:39 ----------------------------------------------- Quantidade de eventos de no mes: 2 (criado a partir da solicitação 4165694)",
        "usuario_final_afetado": "CAWA",
        "departamento": "PSG - PRODUCAO TI",
        "problema_vinculado": "null",
        "incidente_pai": "4165694",
        "causado_pela_rdm": "null",
        "origem": "PortoNet",
        "ticket_sis_ext": "null"
    },
    {
        "numero": "4165687",
        "resumo": "FAILED na aplicacao SAUDE_CARTAO_DAILY_17 job DNET_502_SOLICITACAO_CENTRAL_ITAU qualifier 0001 geracao 1256",
        "severidade": "2",
        "categoria": "Sistemas.Batch.Saude.Normal",
        "status": "Resolvido",
        "grupo_executor": "EQUIPE TCS - TI SAUDE/ODONTO/PORTOMED/FSI",
        "responsavel": "LEANDRO CAETANO DA SILVA",
        "violacao_projetada": "null",
        "violado": "Não",
        "localidade": "DATACENTER - 3º",
        "data_abertura": "16/04/2020 20:01:51",
        "ultima_atualizacao": "17/04/2020 23:31:01",
        "retorno_chamado": "null",
        "classificacao_final": "Incidente",
        "data_resolucao": "17/04/2020 23:30:31",
        "descricao": "Tipo de Desvio: FAILED Aplicacao: SAUDE_CARTAO_DAILY_17 Jobname: DNET_502_SOLICITACAO_CENTRAL_ITAU Qualifier: 0001 Geracao: 1256 Servidor: NT1044 Data: 16/04/2020 19:58:39 ----------------------------------------------- Quantidade de eventos de no mes: 2 (criado a partir da solicitação 4165694)",
        "usuario_final_afetado": "CAWA",
        "departamento": "PSG - PRODUCAO TI",
        "problema_vinculado": "null",
        "incidente_pai": "4165694",
        "causado_pela_rdm": "null",
        "origem": "PortoNet",
        "ticket_sis_ext": "null"
    },
    {
        "numero": "4165687",
        "resumo": "FAILED na aplicacao SAUDE_CARTAO_DAILY_17 job DNET_502_SOLICITACAO_CENTRAL_ITAU qualifier 0001 geracao 1256",
        "severidade": "2",
        "categoria": "Sistemas.Batch.Saude.Normal",
        "status": "Resolvido",
        "grupo_executor": "EQUIPE TCS - TI SAUDE/ODONTO/PORTOMED/FSI",
        "responsavel": "LEANDRO CAETANO DA SILVA",
        "violacao_projetada": "null",
        "violado": "Não",
        "localidade": "DATACENTER - 3º",
        "data_abertura": "16/04/2020 20:01:51",
        "ultima_atualizacao": "17/04/2020 23:31:01",
        "retorno_chamado": "null",
        "classificacao_final": "Incidente",
        "data_resolucao": "17/04/2020 23:30:31",
        "descricao": "Tipo de Desvio: FAILED Aplicacao: SAUDE_CARTAO_DAILY_17 Jobname: DNET_502_SOLICITACAO_CENTRAL_ITAU Qualifier: 0001 Geracao: 1256 Servidor: NT1044 Data: 16/04/2020 19:58:39 ----------------------------------------------- Quantidade de eventos de no mes: 2 (criado a partir da solicitação 4165694)",
        "usuario_final_afetado": "CAWA",
        "departamento": "PSG - PRODUCAO TI",
        "problema_vinculado": "null",
        "incidente_pai": "4165694",
        "causado_pela_rdm": "null",
        "origem": "PortoNet",
        "ticket_sis_ext": "null"
    },
    {
        "numero": "4165687",
        "resumo": "FAILED na aplicacao SAUDE_CARTAO_DAILY_17 job DNET_502_SOLICITACAO_CENTRAL_ITAU qualifier 0001 geracao 1256",
        "severidade": "2",
        "categoria": "Sistemas.Batch.Saude.Normal",
        "status": "Resolvido",
        "grupo_executor": "EQUIPE TCS - TI SAUDE/ODONTO/PORTOMED/FSI",
        "responsavel": "LEANDRO CAETANO DA SILVA",
        "violacao_projetada": "null",
        "violado": "Não",
        "localidade": "DATACENTER - 3º",
        "data_abertura": "16/04/2020 20:01:51",
        "ultima_atualizacao": "17/04/2020 23:31:01",
        "retorno_chamado": "null",
        "classificacao_final": "Incidente",
        "data_resolucao": "17/04/2020 23:30:31",
        "descricao": "Tipo de Desvio: FAILED Aplicacao: SAUDE_CARTAO_DAILY_17 Jobname: DNET_502_SOLICITACAO_CENTRAL_ITAU Qualifier: 0001 Geracao: 1256 Servidor: NT1044 Data: 16/04/2020 19:58:39 ----------------------------------------------- Quantidade de eventos de no mes: 2 (criado a partir da solicitação 4165694)",
        "usuario_final_afetado": "CAWA",
        "departamento": "PSG - PRODUCAO TI",
        "problema_vinculado": "null",
        "incidente_pai": "4165694",
        "causado_pela_rdm": "null",
        "origem": "PortoNet",
        "ticket_sis_ext": "null"
    },
    {
        "numero": "4165687",
        "resumo": "FAILED na aplicacao SAUDE_CARTAO_DAILY_17 job DNET_502_SOLICITACAO_CENTRAL_ITAU qualifier 0001 geracao 1256",
        "severidade": "2",
        "categoria": "Sistemas.Batch.Saude.Normal",
        "status": "Resolvido",
        "grupo_executor": "EQUIPE TCS - TI SAUDE/ODONTO/PORTOMED/FSI",
        "responsavel": "LEANDRO CAETANO DA SILVA",
        "violacao_projetada": "null",
        "violado": "Não",
        "localidade": "DATACENTER - 3º",
        "data_abertura": "16/04/2020 20:01:51",
        "ultima_atualizacao": "17/04/2020 23:31:01",
        "retorno_chamado": "null",
        "classificacao_final": "Incidente",
        "data_resolucao": "17/04/2020 23:30:31",
        "descricao": "Tipo de Desvio: FAILED Aplicacao: SAUDE_CARTAO_DAILY_17 Jobname: DNET_502_SOLICITACAO_CENTRAL_ITAU Qualifier: 0001 Geracao: 1256 Servidor: NT1044 Data: 16/04/2020 19:58:39 ----------------------------------------------- Quantidade de eventos de no mes: 2 (criado a partir da solicitação 4165694)",
        "usuario_final_afetado": "CAWA",
        "departamento": "PSG - PRODUCAO TI",
        "problema_vinculado": "null",
        "incidente_pai": "4165694",
        "causado_pela_rdm": "null",
        "origem": "PortoNet",
        "ticket_sis_ext": "null"
    },
    {
        "numero": "4165687",
        "resumo": "FAILED na aplicacao SAUDE_CARTAO_DAILY_17 job DNET_502_SOLICITACAO_CENTRAL_ITAU qualifier 0001 geracao 1256",
        "severidade": "2",
        "categoria": "Sistemas.Batch.Saude.Normal",
        "status": "Resolvido",
        "grupo_executor": "EQUIPE TCS - TI SAUDE/ODONTO/PORTOMED/FSI",
        "responsavel": "LEANDRO CAETANO DA SILVA",
        "violacao_projetada": "null",
        "violado": "Não",
        "localidade": "DATACENTER - 3º",
        "data_abertura": "16/04/2020 20:01:51",
        "ultima_atualizacao": "17/04/2020 23:31:01",
        "retorno_chamado": "null",
        "classificacao_final": "Incidente",
        "data_resolucao": "17/04/2020 23:30:31",
        "descricao": "Tipo de Desvio: FAILED Aplicacao: SAUDE_CARTAO_DAILY_17 Jobname: DNET_502_SOLICITACAO_CENTRAL_ITAU Qualifier: 0001 Geracao: 1256 Servidor: NT1044 Data: 16/04/2020 19:58:39 ----------------------------------------------- Quantidade de eventos de no mes: 2 (criado a partir da solicitação 4165694)",
        "usuario_final_afetado": "CAWA",
        "departamento": "PSG - PRODUCAO TI",
        "problema_vinculado": "null",
        "incidente_pai": "4165694",
        "causado_pela_rdm": "null",
        "origem": "PortoNet",
        "ticket_sis_ext": "null"
    },
    {
        "numero": "4165687",
        "resumo": "FAILED na aplicacao SAUDE_CARTAO_DAILY_17 job DNET_502_SOLICITACAO_CENTRAL_ITAU qualifier 0001 geracao 1256",
        "severidade": "2",
        "categoria": "Sistemas.Batch.Saude.Normal",
        "status": "Resolvido",
        "grupo_executor": "EQUIPE TCS - TI SAUDE/ODONTO/PORTOMED/FSI",
        "responsavel": "LEANDRO CAETANO DA SILVA",
        "violacao_projetada": "null",
        "violado": "Não",
        "localidade": "DATACENTER - 3º",
        "data_abertura": "16/04/2020 20:01:51",
        "ultima_atualizacao": "17/04/2020 23:31:01",
        "retorno_chamado": "null",
        "classificacao_final": "Incidente",
        "data_resolucao": "17/04/2020 23:30:31",
        "descricao": "Tipo de Desvio: FAILED Aplicacao: SAUDE_CARTAO_DAILY_17 Jobname: DNET_502_SOLICITACAO_CENTRAL_ITAU Qualifier: 0001 Geracao: 1256 Servidor: NT1044 Data: 16/04/2020 19:58:39 ----------------------------------------------- Quantidade de eventos de no mes: 2 (criado a partir da solicitação 4165694)",
        "usuario_final_afetado": "CAWA",
        "departamento": "PSG - PRODUCAO TI",
        "problema_vinculado": "null",
        "incidente_pai": "4165694",
        "causado_pela_rdm": "null",
        "origem": "PortoNet",
        "ticket_sis_ext": "null"
    },
    {
        "numero": "4165687",
        "resumo": "FAILED na aplicacao SAUDE_CARTAO_DAILY_17 job DNET_502_SOLICITACAO_CENTRAL_ITAU qualifier 0001 geracao 1256",
        "severidade": "2",
        "categoria": "Sistemas.Batch.Saude.Normal",
        "status": "Resolvido",
        "grupo_executor": "EQUIPE TCS - TI SAUDE/ODONTO/PORTOMED/FSI",
        "responsavel": "LEANDRO CAETANO DA SILVA",
        "violacao_projetada": "null",
        "violado": "Não",
        "localidade": "DATACENTER - 3º",
        "data_abertura": "16/04/2020 20:01:51",
        "ultima_atualizacao": "17/04/2020 23:31:01",
        "retorno_chamado": "null",
        "classificacao_final": "Incidente",
        "data_resolucao": "17/04/2020 23:30:31",
        "descricao": "Tipo de Desvio: FAILED Aplicacao: SAUDE_CARTAO_DAILY_17 Jobname: DNET_502_SOLICITACAO_CENTRAL_ITAU Qualifier: 0001 Geracao: 1256 Servidor: NT1044 Data: 16/04/2020 19:58:39 ----------------------------------------------- Quantidade de eventos de no mes: 2 (criado a partir da solicitação 4165694)",
        "usuario_final_afetado": "CAWA",
        "departamento": "PSG - PRODUCAO TI",
        "problema_vinculado": "null",
        "incidente_pai": "4165694",
        "causado_pela_rdm": "null",
        "origem": "PortoNet",
        "ticket_sis_ext": "null"
    },
    {
        "numero": "4165687",
        "resumo": "FAILED na aplicacao SAUDE_CARTAO_DAILY_17 job DNET_502_SOLICITACAO_CENTRAL_ITAU qualifier 0001 geracao 1256",
        "severidade": "2",
        "categoria": "Sistemas.Batch.Saude.Normal",
        "status": "Resolvido",
        "grupo_executor": "EQUIPE TCS - TI SAUDE/ODONTO/PORTOMED/FSI",
        "responsavel": "LEANDRO CAETANO DA SILVA",
        "violacao_projetada": "null",
        "violado": "Não",
        "localidade": "DATACENTER - 3º",
        "data_abertura": "16/04/2020 20:01:51",
        "ultima_atualizacao": "17/04/2020 23:31:01",
        "retorno_chamado": "null",
        "classificacao_final": "Incidente",
        "data_resolucao": "17/04/2020 23:30:31",
        "descricao": "Tipo de Desvio: FAILED Aplicacao: SAUDE_CARTAO_DAILY_17 Jobname: DNET_502_SOLICITACAO_CENTRAL_ITAU Qualifier: 0001 Geracao: 1256 Servidor: NT1044 Data: 16/04/2020 19:58:39 ----------------------------------------------- Quantidade de eventos de no mes: 2 (criado a partir da solicitação 4165694)",
        "usuario_final_afetado": "CAWA",
        "departamento": "PSG - PRODUCAO TI",
        "problema_vinculado": "null",
        "incidente_pai": "4165694",
        "causado_pela_rdm": "null",
        "origem": "PortoNet",
        "ticket_sis_ext": "null"
    },
    {
        "numero": "4165687",
        "resumo": "FAILED na aplicacao SAUDE_CARTAO_DAILY_17 job DNET_502_SOLICITACAO_CENTRAL_ITAU qualifier 0001 geracao 1256",
        "severidade": "2",
        "categoria": "Sistemas.Batch.Saude.Normal",
        "status": "Resolvido",
        "grupo_executor": "EQUIPE TCS - TI SAUDE/ODONTO/PORTOMED/FSI",
        "responsavel": "LEANDRO CAETANO DA SILVA",
        "violacao_projetada": "null",
        "violado": "Não",
        "localidade": "DATACENTER - 3º",
        "data_abertura": "16/04/2020 20:01:51",
        "ultima_atualizacao": "17/04/2020 23:31:01",
        "retorno_chamado": "null",
        "classificacao_final": "Incidente",
        "data_resolucao": "17/04/2020 23:30:31",
        "descricao": "Tipo de Desvio: FAILED Aplicacao: SAUDE_CARTAO_DAILY_17 Jobname: DNET_502_SOLICITACAO_CENTRAL_ITAU Qualifier: 0001 Geracao: 1256 Servidor: NT1044 Data: 16/04/2020 19:58:39 ----------------------------------------------- Quantidade de eventos de no mes: 2 (criado a partir da solicitação 4165694)",
        "usuario_final_afetado": "CAWA",
        "departamento": "PSG - PRODUCAO TI",
        "problema_vinculado": "null",
        "incidente_pai": "4165694",
        "causado_pela_rdm": "null",
        "origem": "PortoNet",
        "ticket_sis_ext": "null"
    },
    {
        "numero": "4165687",
        "resumo": "FAILED na aplicacao SAUDE_CARTAO_DAILY_17 job DNET_502_SOLICITACAO_CENTRAL_ITAU qualifier 0001 geracao 1256",
        "severidade": "2",
        "categoria": "Sistemas.Batch.Saude.Normal",
        "status": "Resolvido",
        "grupo_executor": "EQUIPE TCS - TI SAUDE/ODONTO/PORTOMED/FSI",
        "responsavel": "LEANDRO CAETANO DA SILVA",
        "violacao_projetada": "null",
        "violado": "Não",
        "localidade": "DATACENTER - 3º",
        "data_abertura": "16/04/2020 20:01:51",
        "ultima_atualizacao": "17/04/2020 23:31:01",
        "retorno_chamado": "null",
        "classificacao_final": "Incidente",
        "data_resolucao": "17/04/2020 23:30:31",
        "descricao": "Tipo de Desvio: FAILED Aplicacao: SAUDE_CARTAO_DAILY_17 Jobname: DNET_502_SOLICITACAO_CENTRAL_ITAU Qualifier: 0001 Geracao: 1256 Servidor: NT1044 Data: 16/04/2020 19:58:39 ----------------------------------------------- Quantidade de eventos de no mes: 2 (criado a partir da solicitação 4165694)",
        "usuario_final_afetado": "CAWA",
        "departamento": "PSG - PRODUCAO TI",
        "problema_vinculado": "null",
        "incidente_pai": "4165694",
        "causado_pela_rdm": "null",
        "origem": "PortoNet",
        "ticket_sis_ext": "null"
    },
    {
        "numero": "4165687",
        "resumo": "FAILED na aplicacao SAUDE_CARTAO_DAILY_17 job DNET_502_SOLICITACAO_CENTRAL_ITAU qualifier 0001 geracao 1256",
        "severidade": "2",
        "categoria": "Sistemas.Batch.Saude.Normal",
        "status": "Resolvido",
        "grupo_executor": "EQUIPE TCS - TI SAUDE/ODONTO/PORTOMED/FSI",
        "responsavel": "LEANDRO CAETANO DA SILVA",
        "violacao_projetada": "null",
        "violado": "Não",
        "localidade": "DATACENTER - 3º",
        "data_abertura": "16/04/2020 20:01:51",
        "ultima_atualizacao": "17/04/2020 23:31:01",
        "retorno_chamado": "null",
        "classificacao_final": "Incidente",
        "data_resolucao": "17/04/2020 23:30:31",
        "descricao": "Tipo de Desvio: FAILED Aplicacao: SAUDE_CARTAO_DAILY_17 Jobname: DNET_502_SOLICITACAO_CENTRAL_ITAU Qualifier: 0001 Geracao: 1256 Servidor: NT1044 Data: 16/04/2020 19:58:39 ----------------------------------------------- Quantidade de eventos de no mes: 2 (criado a partir da solicitação 4165694)",
        "usuario_final_afetado": "CAWA",
        "departamento": "PSG - PRODUCAO TI",
        "problema_vinculado": "null",
        "incidente_pai": "4165694",
        "causado_pela_rdm": "null",
        "origem": "PortoNet",
        "ticket_sis_ext": "null"
    },
    {
        "numero": "4165687",
        "resumo": "FAILED na aplicacao SAUDE_CARTAO_DAILY_17 job DNET_502_SOLICITACAO_CENTRAL_ITAU qualifier 0001 geracao 1256",
        "severidade": "2",
        "categoria": "Sistemas.Batch.Saude.Normal",
        "status": "Resolvido",
        "grupo_executor": "EQUIPE TCS - TI SAUDE/ODONTO/PORTOMED/FSI",
        "responsavel": "LEANDRO CAETANO DA SILVA",
        "violacao_projetada": "null",
        "violado": "Não",
        "localidade": "DATACENTER - 3º",
        "data_abertura": "16/04/2020 20:01:51",
        "ultima_atualizacao": "17/04/2020 23:31:01",
        "retorno_chamado": "null",
        "classificacao_final": "Incidente",
        "data_resolucao": "17/04/2020 23:30:31",
        "descricao": "Tipo de Desvio: FAILED Aplicacao: SAUDE_CARTAO_DAILY_17 Jobname: DNET_502_SOLICITACAO_CENTRAL_ITAU Qualifier: 0001 Geracao: 1256 Servidor: NT1044 Data: 16/04/2020 19:58:39 ----------------------------------------------- Quantidade de eventos de no mes: 2 (criado a partir da solicitação 4165694)",
        "usuario_final_afetado": "CAWA",
        "departamento": "PSG - PRODUCAO TI",
        "problema_vinculado": "null",
        "incidente_pai": "4165694",
        "causado_pela_rdm": "null",
        "origem": "PortoNet",
        "ticket_sis_ext": "null"
    },
    {
        "numero": "4165687",
        "resumo": "FAILED na aplicacao SAUDE_CARTAO_DAILY_17 job DNET_502_SOLICITACAO_CENTRAL_ITAU qualifier 0001 geracao 1256",
        "severidade": "2",
        "categoria": "Sistemas.Batch.Saude.Normal",
        "status": "Resolvido",
        "grupo_executor": "EQUIPE TCS - TI SAUDE/ODONTO/PORTOMED/FSI",
        "responsavel": "LEANDRO CAETANO DA SILVA",
        "violacao_projetada": "null",
        "violado": "Não",
        "localidade": "DATACENTER - 3º",
        "data_abertura": "16/04/2020 20:01:51",
        "ultima_atualizacao": "17/04/2020 23:31:01",
        "retorno_chamado": "null",
        "classificacao_final": "Incidente",
        "data_resolucao": "17/04/2020 23:30:31",
        "descricao": "Tipo de Desvio: FAILED Aplicacao: SAUDE_CARTAO_DAILY_17 Jobname: DNET_502_SOLICITACAO_CENTRAL_ITAU Qualifier: 0001 Geracao: 1256 Servidor: NT1044 Data: 16/04/2020 19:58:39 ----------------------------------------------- Quantidade de eventos de no mes: 2 (criado a partir da solicitação 4165694)",
        "usuario_final_afetado": "CAWA",
        "departamento": "PSG - PRODUCAO TI",
        "problema_vinculado": "null",
        "incidente_pai": "4165694",
        "causado_pela_rdm": "null",
        "origem": "PortoNet",
        "ticket_sis_ext": "null"
    },
    {
        "numero": "4165687",
        "resumo": "FAILED na aplicacao SAUDE_CARTAO_DAILY_17 job DNET_502_SOLICITACAO_CENTRAL_ITAU qualifier 0001 geracao 1256",
        "severidade": "2",
        "categoria": "Sistemas.Batch.Saude.Normal",
        "status": "Resolvido",
        "grupo_executor": "EQUIPE TCS - TI SAUDE/ODONTO/PORTOMED/FSI",
        "responsavel": "LEANDRO CAETANO DA SILVA",
        "violacao_projetada": "null",
        "violado": "Não",
        "localidade": "DATACENTER - 3º",
        "data_abertura": "16/04/2020 20:01:51",
        "ultima_atualizacao": "17/04/2020 23:31:01",
        "retorno_chamado": "null",
        "classificacao_final": "Incidente",
        "data_resolucao": "17/04/2020 23:30:31",
        "descricao": "Tipo de Desvio: FAILED Aplicacao: SAUDE_CARTAO_DAILY_17 Jobname: DNET_502_SOLICITACAO_CENTRAL_ITAU Qualifier: 0001 Geracao: 1256 Servidor: NT1044 Data: 16/04/2020 19:58:39 ----------------------------------------------- Quantidade de eventos de no mes: 2 (criado a partir da solicitação 4165694)",
        "usuario_final_afetado": "CAWA",
        "departamento": "PSG - PRODUCAO TI",
        "problema_vinculado": "null",
        "incidente_pai": "4165694",
        "causado_pela_rdm": "null",
        "origem": "PortoNet",
        "ticket_sis_ext": "null"
    },
    {
        "numero": "4165687",
        "resumo": "FAILED na aplicacao SAUDE_CARTAO_DAILY_17 job DNET_502_SOLICITACAO_CENTRAL_ITAU qualifier 0001 geracao 1256",
        "severidade": "2",
        "categoria": "Sistemas.Batch.Saude.Normal",
        "status": "Resolvido",
        "grupo_executor": "EQUIPE TCS - TI SAUDE/ODONTO/PORTOMED/FSI",
        "responsavel": "LEANDRO CAETANO DA SILVA",
        "violacao_projetada": "null",
        "violado": "Não",
        "localidade": "DATACENTER - 3º",
        "data_abertura": "16/04/2020 20:01:51",
        "ultima_atualizacao": "17/04/2020 23:31:01",
        "retorno_chamado": "null",
        "classificacao_final": "Incidente",
        "data_resolucao": "17/04/2020 23:30:31",
        "descricao": "Tipo de Desvio: FAILED Aplicacao: SAUDE_CARTAO_DAILY_17 Jobname: DNET_502_SOLICITACAO_CENTRAL_ITAU Qualifier: 0001 Geracao: 1256 Servidor: NT1044 Data: 16/04/2020 19:58:39 ----------------------------------------------- Quantidade de eventos de no mes: 2 (criado a partir da solicitação 4165694)",
        "usuario_final_afetado": "CAWA",
        "departamento": "PSG - PRODUCAO TI",
        "problema_vinculado": "null",
        "incidente_pai": "4165694",
        "causado_pela_rdm": "null",
        "origem": "PortoNet",
        "ticket_sis_ext": "null"
    },
    {
        "numero": "4165687",
        "resumo": "FAILED na aplicacao SAUDE_CARTAO_DAILY_17 job DNET_502_SOLICITACAO_CENTRAL_ITAU qualifier 0001 geracao 1256",
        "severidade": "2",
        "categoria": "Sistemas.Batch.Saude.Normal",
        "status": "Resolvido",
        "grupo_executor": "EQUIPE TCS - TI SAUDE/ODONTO/PORTOMED/FSI",
        "responsavel": "LEANDRO CAETANO DA SILVA",
        "violacao_projetada": "null",
        "violado": "Não",
        "localidade": "DATACENTER - 3º",
        "data_abertura": "16/04/2020 20:01:51",
        "ultima_atualizacao": "17/04/2020 23:31:01",
        "retorno_chamado": "null",
        "classificacao_final": "Incidente",
        "data_resolucao": "17/04/2020 23:30:31",
        "descricao": "Tipo de Desvio: FAILED Aplicacao: SAUDE_CARTAO_DAILY_17 Jobname: DNET_502_SOLICITACAO_CENTRAL_ITAU Qualifier: 0001 Geracao: 1256 Servidor: NT1044 Data: 16/04/2020 19:58:39 ----------------------------------------------- Quantidade de eventos de no mes: 2 (criado a partir da solicitação 4165694)",
        "usuario_final_afetado": "CAWA",
        "departamento": "PSG - PRODUCAO TI",
        "problema_vinculado": "null",
        "incidente_pai": "4165694",
        "causado_pela_rdm": "null",
        "origem": "PortoNet",
        "ticket_sis_ext": "null"
    },
    {
        "numero": "4137514 *",
        "resumo": "GSS - Erro na Mudança de Fase do Protocolo",
        "severidade": "2",
        "categoria": "Sistemas.Saúde e Odonto.Apollo.Contas Médicas.Erro.Mudança de fase",
        "status": "Resolvido",
        "grupo_executor": "EQUIPE TCS - TI SAUDE/ODONTO/PORTOMED/FSI",
        "responsavel": "ERALDO CANUTO DE SOUZA",
        "violacao_projetada": "null",
        "violado": "Não",
        "localidade": "GUAIANASES - 8º LADO A",
        "data_abertura": "02/04/2020 15:54:22",
        "ultima_atualizacao": "16/04/2020 14:18:19",
        "retorno_chamado": "null",
        "classificacao_final": "Incidente",
        "data_resolucao": "15/04/2020 16:32:34",
        "descricao": "Prezados, estamos com Erro na Mudança de Fase dos protocolos 9897006,9897000,9896990,9894300, ao processar a mudança o mesmo está apresentando a divergência (One or more errors occurred.). Ao tentar Editar o Regime de Atendimento do protocolo o mesmo apresenta Erro 500 (Falha no Serviço da Aplicação). Solicitamos Urgência nestes casos, pois estes processos devem ser analisados até o dia 08/04/2020 para não impactarmos no pagamento para o prestador em 20/04/2020. Server Error in '/contas' Application. ________________________________________ Falha no serviço da aplicação Description: An unhandled exception occurred during the execution of the current web request. Please review the stack trace for more information about the error and where it originated in the code. Exception Details: System.ServiceModel.FaultException`1[[Porto.Saude.Contas.Services.References.Fases.AutoGenClient.MudancaFaseService.runtimeFault, Porto.Saude.Contas.Services.References, Version=0.0.7396.22566, Culture=neutral, PublicKeyToken=null]]: Falha no serviço da aplicação Source Error: An unhandled exception was generated during the execution of the current web request. Information regarding the origin and location of the exception can be identified using the exception stack trace below. Stack Trace: [FaultException`1: Falha no serviço da aplicação] System.Runtime.Remoting.Proxies.RealProxy.HandleReturnMessage(IMessage reqMsg, IMessage retMsg) +348 System.Runtime.Remoting.Proxies.RealProxy.PrivateInvoke(MessageData& msgData, Int32 type) +1351 Porto.Saude.Contas.Services.References.Fases.AutoGenClient.MudancaFaseService.IMudancaFaseService.reprocessarPeg(reprocessarPegRequest request) +0 Porto.Saude.Contas.Services.References.Fases.AutoGenClient.MudancaFaseService.MudancaFaseServiceClient.Porto.Saude.Contas.Services.References.Fases.AutoGenClient.MudancaFaseService.IMudancaFaseService.reprocessarPeg(reprocessarPegRequest request) +189 Porto.Saude.Contas.Services.References.Fases.AutoGenClient.MudancaFaseService.MudancaFaseServiceClient.reprocessarPeg(pegId peg, usuarioId usuario, List`1& ocorrencias) +91 Porto.Saude.Contas.Portal.Business.ComandosPeg.Reprocessamento.ReprocessarPeg(Int64 codigoPeg) +195 Porto.Saude.Contas.Portal.Business.Pegs.Digitacao.Validacoes.ReprocessaPeg.Executar(PegContext context) +65 Porto.Saude.Contas.Portal.Business.Pegs.Digitacao.ValidadorDigitacaoPeg.ProcessarRegrasAposSalvar() +266 Porto.Saude.Contas.Portal.Areas.Pegs.Controllers.PegController.Editar(PegBaseViewModel viewModel) +824 lambda_method(Closure , ControllerBase , Object[] ) +127 System.Web.Mvc.ReflectedActionDescriptor.Execute(ControllerContext controllerContext, IDictionary`2 parameters) +249 System.Web.Mvc.ControllerActionInvoker.InvokeActionMethod(ControllerContext controllerContext, ActionDescriptor actionDescriptor, IDictionary`2 parameters) +39 System.Web.Mvc.Async.<>c__DisplayClass39.b__33() +87 System.Web.Mvc.Async.<>c__DisplayClass4f.b__49() +439 System.Web.Mvc.Async.<>c__DisplayClass4f.b__49() +439 System.Web.Mvc.Async.<>c__DisplayClass37.b__36(IAsyncResult asyncResult) +15 System.Web.Mvc.Async.<>c__DisplayClass2a.b__20() +34 System.Web.Mvc.Async.<>c__DisplayClass25.b__22(IAsyncResult asyncResult) +221 System.Web.Mvc.<>c__DisplayClass1d.b__18(IAsyncResult asyncResult) +28 System.Web.Mvc.Async.<>c__DisplayClass4.b__3(IAsyncResult ar) +15 System.Web.Mvc.Controller.EndExecuteCore(IAsyncResult asyncResult) +42 System.Web.Mvc.Async.<>c__DisplayClass4.b__3(IAsyncResult ar) +15 System.Web.Mvc.Controller.EndExecute(IAsyncResult asyncResult) +369 System.Web.Mvc.<>c__DisplayClass8.b__3(IAsyncResult asyncResult) +42 System.Web.",
        "usuario_final_afetado": "JOSE LIMEIRA DA SILVA JUNIOR",
        "departamento": "PSA - GESTAO SERVICOS SAUDE E OCUPACIONAL - 010014630",
        "problema_vinculado": "4162338",
        "incidente_pai": "null",
        "causado_pela_rdm": "null",
        "origem": "PortoNet",
        "ticket_sis_ext": "null"
    },
    {
        "numero": "4137514 *",
        "resumo": "GSS - Erro na Mudança de Fase do Protocolo",
        "severidade": "2",
        "categoria": "Sistemas.Saúde e Odonto.Apollo.Contas Médicas.Erro.Mudança de fase",
        "status": "Resolvido",
        "grupo_executor": "EQUIPE TCS - TI SAUDE/ODONTO/PORTOMED/FSI",
        "responsavel": "ERALDO CANUTO DE SOUZA",
        "violacao_projetada": "null",
        "violado": "Não",
        "localidade": "GUAIANASES - 8º LADO A",
        "data_abertura": "02/04/2020 15:54:22",
        "ultima_atualizacao": "16/04/2020 14:18:19",
        "retorno_chamado": "null",
        "classificacao_final": "Incidente",
        "data_resolucao": "15/04/2020 16:32:34",
        "descricao": "Prezados, estamos com Erro na Mudança de Fase dos protocolos 9897006,9897000,9896990,9894300, ao processar a mudança o mesmo está apresentando a divergência (One or more errors occurred.). Ao tentar Editar o Regime de Atendimento do protocolo o mesmo apresenta Erro 500 (Falha no Serviço da Aplicação). Solicitamos Urgência nestes casos, pois estes processos devem ser analisados até o dia 08/04/2020 para não impactarmos no pagamento para o prestador em 20/04/2020. Server Error in '/contas' Application. ________________________________________ Falha no serviço da aplicação Description: An unhandled exception occurred during the execution of the current web request. Please review the stack trace for more information about the error and where it originated in the code. Exception Details: System.ServiceModel.FaultException`1[[Porto.Saude.Contas.Services.References.Fases.AutoGenClient.MudancaFaseService.runtimeFault, Porto.Saude.Contas.Services.References, Version=0.0.7396.22566, Culture=neutral, PublicKeyToken=null]]: Falha no serviço da aplicação Source Error: An unhandled exception was generated during the execution of the current web request. Information regarding the origin and location of the exception can be identified using the exception stack trace below. Stack Trace: [FaultException`1: Falha no serviço da aplicação] System.Runtime.Remoting.Proxies.RealProxy.HandleReturnMessage(IMessage reqMsg, IMessage retMsg) +348 System.Runtime.Remoting.Proxies.RealProxy.PrivateInvoke(MessageData& msgData, Int32 type) +1351 Porto.Saude.Contas.Services.References.Fases.AutoGenClient.MudancaFaseService.IMudancaFaseService.reprocessarPeg(reprocessarPegRequest request) +0 Porto.Saude.Contas.Services.References.Fases.AutoGenClient.MudancaFaseService.MudancaFaseServiceClient.Porto.Saude.Contas.Services.References.Fases.AutoGenClient.MudancaFaseService.IMudancaFaseService.reprocessarPeg(reprocessarPegRequest request) +189 Porto.Saude.Contas.Services.References.Fases.AutoGenClient.MudancaFaseService.MudancaFaseServiceClient.reprocessarPeg(pegId peg, usuarioId usuario, List`1& ocorrencias) +91 Porto.Saude.Contas.Portal.Business.ComandosPeg.Reprocessamento.ReprocessarPeg(Int64 codigoPeg) +195 Porto.Saude.Contas.Portal.Business.Pegs.Digitacao.Validacoes.ReprocessaPeg.Executar(PegContext context) +65 Porto.Saude.Contas.Portal.Business.Pegs.Digitacao.ValidadorDigitacaoPeg.ProcessarRegrasAposSalvar() +266 Porto.Saude.Contas.Portal.Areas.Pegs.Controllers.PegController.Editar(PegBaseViewModel viewModel) +824 lambda_method(Closure , ControllerBase , Object[] ) +127 System.Web.Mvc.ReflectedActionDescriptor.Execute(ControllerContext controllerContext, IDictionary`2 parameters) +249 System.Web.Mvc.ControllerActionInvoker.InvokeActionMethod(ControllerContext controllerContext, ActionDescriptor actionDescriptor, IDictionary`2 parameters) +39 System.Web.Mvc.Async.<>c__DisplayClass39.b__33() +87 System.Web.Mvc.Async.<>c__DisplayClass4f.b__49() +439 System.Web.Mvc.Async.<>c__DisplayClass4f.b__49() +439 System.Web.Mvc.Async.<>c__DisplayClass37.b__36(IAsyncResult asyncResult) +15 System.Web.Mvc.Async.<>c__DisplayClass2a.b__20() +34 System.Web.Mvc.Async.<>c__DisplayClass25.b__22(IAsyncResult asyncResult) +221 System.Web.Mvc.<>c__DisplayClass1d.b__18(IAsyncResult asyncResult) +28 System.Web.Mvc.Async.<>c__DisplayClass4.b__3(IAsyncResult ar) +15 System.Web.Mvc.Controller.EndExecuteCore(IAsyncResult asyncResult) +42 System.Web.Mvc.Async.<>c__DisplayClass4.b__3(IAsyncResult ar) +15 System.Web.Mvc.Controller.EndExecute(IAsyncResult asyncResult) +369 System.Web.Mvc.<>c__DisplayClass8.b__3(IAsyncResult asyncResult) +42 System.Web.",
        "usuario_final_afetado": "JOSE LIMEIRA DA SILVA JUNIOR",
        "departamento": "PSA - GESTAO SERVICOS SAUDE E OCUPACIONAL - 010014630",
        "problema_vinculado": "4162338",
        "incidente_pai": "null",
        "causado_pela_rdm": "null",
        "origem": "PortoNet",
        "ticket_sis_ext": "null"
    },
    {
        "numero": "4137514 *",
        "resumo": "GSS - Erro na Mudança de Fase do Protocolo",
        "severidade": "2",
        "categoria": "Sistemas.Saúde e Odonto.Apollo.Contas Médicas.Erro.Mudança de fase",
        "status": "Resolvido",
        "grupo_executor": "EQUIPE TCS - TI SAUDE/ODONTO/PORTOMED/FSI",
        "responsavel": "ERALDO CANUTO DE SOUZA",
        "violacao_projetada": "null",
        "violado": "Não",
        "localidade": "GUAIANASES - 8º LADO A",
        "data_abertura": "02/04/2020 15:54:22",
        "ultima_atualizacao": "16/04/2020 14:18:19",
        "retorno_chamado": "null",
        "classificacao_final": "Incidente",
        "data_resolucao": "15/04/2020 16:32:34",
        "descricao": "Prezados, estamos com Erro na Mudança de Fase dos protocolos 9897006,9897000,9896990,9894300, ao processar a mudança o mesmo está apresentando a divergência (One or more errors occurred.). Ao tentar Editar o Regime de Atendimento do protocolo o mesmo apresenta Erro 500 (Falha no Serviço da Aplicação). Solicitamos Urgência nestes casos, pois estes processos devem ser analisados até o dia 08/04/2020 para não impactarmos no pagamento para o prestador em 20/04/2020. Server Error in '/contas' Application. ________________________________________ Falha no serviço da aplicação Description: An unhandled exception occurred during the execution of the current web request. Please review the stack trace for more information about the error and where it originated in the code. Exception Details: System.ServiceModel.FaultException`1[[Porto.Saude.Contas.Services.References.Fases.AutoGenClient.MudancaFaseService.runtimeFault, Porto.Saude.Contas.Services.References, Version=0.0.7396.22566, Culture=neutral, PublicKeyToken=null]]: Falha no serviço da aplicação Source Error: An unhandled exception was generated during the execution of the current web request. Information regarding the origin and location of the exception can be identified using the exception stack trace below. Stack Trace: [FaultException`1: Falha no serviço da aplicação] System.Runtime.Remoting.Proxies.RealProxy.HandleReturnMessage(IMessage reqMsg, IMessage retMsg) +348 System.Runtime.Remoting.Proxies.RealProxy.PrivateInvoke(MessageData& msgData, Int32 type) +1351 Porto.Saude.Contas.Services.References.Fases.AutoGenClient.MudancaFaseService.IMudancaFaseService.reprocessarPeg(reprocessarPegRequest request) +0 Porto.Saude.Contas.Services.References.Fases.AutoGenClient.MudancaFaseService.MudancaFaseServiceClient.Porto.Saude.Contas.Services.References.Fases.AutoGenClient.MudancaFaseService.IMudancaFaseService.reprocessarPeg(reprocessarPegRequest request) +189 Porto.Saude.Contas.Services.References.Fases.AutoGenClient.MudancaFaseService.MudancaFaseServiceClient.reprocessarPeg(pegId peg, usuarioId usuario, List`1& ocorrencias) +91 Porto.Saude.Contas.Portal.Business.ComandosPeg.Reprocessamento.ReprocessarPeg(Int64 codigoPeg) +195 Porto.Saude.Contas.Portal.Business.Pegs.Digitacao.Validacoes.ReprocessaPeg.Executar(PegContext context) +65 Porto.Saude.Contas.Portal.Business.Pegs.Digitacao.ValidadorDigitacaoPeg.ProcessarRegrasAposSalvar() +266 Porto.Saude.Contas.Portal.Areas.Pegs.Controllers.PegController.Editar(PegBaseViewModel viewModel) +824 lambda_method(Closure , ControllerBase , Object[] ) +127 System.Web.Mvc.ReflectedActionDescriptor.Execute(ControllerContext controllerContext, IDictionary`2 parameters) +249 System.Web.Mvc.ControllerActionInvoker.InvokeActionMethod(ControllerContext controllerContext, ActionDescriptor actionDescriptor, IDictionary`2 parameters) +39 System.Web.Mvc.Async.<>c__DisplayClass39.b__33() +87 System.Web.Mvc.Async.<>c__DisplayClass4f.b__49() +439 System.Web.Mvc.Async.<>c__DisplayClass4f.b__49() +439 System.Web.Mvc.Async.<>c__DisplayClass37.b__36(IAsyncResult asyncResult) +15 System.Web.Mvc.Async.<>c__DisplayClass2a.b__20() +34 System.Web.Mvc.Async.<>c__DisplayClass25.b__22(IAsyncResult asyncResult) +221 System.Web.Mvc.<>c__DisplayClass1d.b__18(IAsyncResult asyncResult) +28 System.Web.Mvc.Async.<>c__DisplayClass4.b__3(IAsyncResult ar) +15 System.Web.Mvc.Controller.EndExecuteCore(IAsyncResult asyncResult) +42 System.Web.Mvc.Async.<>c__DisplayClass4.b__3(IAsyncResult ar) +15 System.Web.Mvc.Controller.EndExecute(IAsyncResult asyncResult) +369 System.Web.Mvc.<>c__DisplayClass8.b__3(IAsyncResult asyncResult) +42 System.Web.",
        "usuario_final_afetado": "JOSE LIMEIRA DA SILVA JUNIOR",
        "departamento": "PSA - GESTAO SERVICOS SAUDE E OCUPACIONAL - 010014630",
        "problema_vinculado": "4162338",
        "incidente_pai": "null",
        "causado_pela_rdm": "null",
        "origem": "PortoNet",
        "ticket_sis_ext": "null"
    },
    {
        "numero": "4137514 *",
        "resumo": "GSS - Erro na Mudança de Fase do Protocolo",
        "severidade": "2",
        "categoria": "Sistemas.Saúde e Odonto.Apollo.Contas Médicas.Erro.Mudança de fase",
        "status": "Resolvido",
        "grupo_executor": "EQUIPE TCS - TI SAUDE/ODONTO/PORTOMED/FSI",
        "responsavel": "ERALDO CANUTO DE SOUZA",
        "violacao_projetada": "null",
        "violado": "Não",
        "localidade": "GUAIANASES - 8º LADO A",
        "data_abertura": "02/04/2020 15:54:22",
        "ultima_atualizacao": "16/04/2020 14:18:19",
        "retorno_chamado": "null",
        "classificacao_final": "Incidente",
        "data_resolucao": "15/04/2020 16:32:34",
        "descricao": "Prezados, estamos com Erro na Mudança de Fase dos protocolos 9897006,9897000,9896990,9894300, ao processar a mudança o mesmo está apresentando a divergência (One or more errors occurred.). Ao tentar Editar o Regime de Atendimento do protocolo o mesmo apresenta Erro 500 (Falha no Serviço da Aplicação). Solicitamos Urgência nestes casos, pois estes processos devem ser analisados até o dia 08/04/2020 para não impactarmos no pagamento para o prestador em 20/04/2020. Server Error in '/contas' Application. ________________________________________ Falha no serviço da aplicação Description: An unhandled exception occurred during the execution of the current web request. Please review the stack trace for more information about the error and where it originated in the code. Exception Details: System.ServiceModel.FaultException`1[[Porto.Saude.Contas.Services.References.Fases.AutoGenClient.MudancaFaseService.runtimeFault, Porto.Saude.Contas.Services.References, Version=0.0.7396.22566, Culture=neutral, PublicKeyToken=null]]: Falha no serviço da aplicação Source Error: An unhandled exception was generated during the execution of the current web request. Information regarding the origin and location of the exception can be identified using the exception stack trace below. Stack Trace: [FaultException`1: Falha no serviço da aplicação] System.Runtime.Remoting.Proxies.RealProxy.HandleReturnMessage(IMessage reqMsg, IMessage retMsg) +348 System.Runtime.Remoting.Proxies.RealProxy.PrivateInvoke(MessageData& msgData, Int32 type) +1351 Porto.Saude.Contas.Services.References.Fases.AutoGenClient.MudancaFaseService.IMudancaFaseService.reprocessarPeg(reprocessarPegRequest request) +0 Porto.Saude.Contas.Services.References.Fases.AutoGenClient.MudancaFaseService.MudancaFaseServiceClient.Porto.Saude.Contas.Services.References.Fases.AutoGenClient.MudancaFaseService.IMudancaFaseService.reprocessarPeg(reprocessarPegRequest request) +189 Porto.Saude.Contas.Services.References.Fases.AutoGenClient.MudancaFaseService.MudancaFaseServiceClient.reprocessarPeg(pegId peg, usuarioId usuario, List`1& ocorrencias) +91 Porto.Saude.Contas.Portal.Business.ComandosPeg.Reprocessamento.ReprocessarPeg(Int64 codigoPeg) +195 Porto.Saude.Contas.Portal.Business.Pegs.Digitacao.Validacoes.ReprocessaPeg.Executar(PegContext context) +65 Porto.Saude.Contas.Portal.Business.Pegs.Digitacao.ValidadorDigitacaoPeg.ProcessarRegrasAposSalvar() +266 Porto.Saude.Contas.Portal.Areas.Pegs.Controllers.PegController.Editar(PegBaseViewModel viewModel) +824 lambda_method(Closure , ControllerBase , Object[] ) +127 System.Web.Mvc.ReflectedActionDescriptor.Execute(ControllerContext controllerContext, IDictionary`2 parameters) +249 System.Web.Mvc.ControllerActionInvoker.InvokeActionMethod(ControllerContext controllerContext, ActionDescriptor actionDescriptor, IDictionary`2 parameters) +39 System.Web.Mvc.Async.<>c__DisplayClass39.b__33() +87 System.Web.Mvc.Async.<>c__DisplayClass4f.b__49() +439 System.Web.Mvc.Async.<>c__DisplayClass4f.b__49() +439 System.Web.Mvc.Async.<>c__DisplayClass37.b__36(IAsyncResult asyncResult) +15 System.Web.Mvc.Async.<>c__DisplayClass2a.b__20() +34 System.Web.Mvc.Async.<>c__DisplayClass25.b__22(IAsyncResult asyncResult) +221 System.Web.Mvc.<>c__DisplayClass1d.b__18(IAsyncResult asyncResult) +28 System.Web.Mvc.Async.<>c__DisplayClass4.b__3(IAsyncResult ar) +15 System.Web.Mvc.Controller.EndExecuteCore(IAsyncResult asyncResult) +42 System.Web.Mvc.Async.<>c__DisplayClass4.b__3(IAsyncResult ar) +15 System.Web.Mvc.Controller.EndExecute(IAsyncResult asyncResult) +369 System.Web.Mvc.<>c__DisplayClass8.b__3(IAsyncResult asyncResult) +42 System.Web.",
        "usuario_final_afetado": "JOSE LIMEIRA DA SILVA JUNIOR",
        "departamento": "PSA - GESTAO SERVICOS SAUDE E OCUPACIONAL - 010014630",
        "problema_vinculado": "4162338",
        "incidente_pai": "null",
        "causado_pela_rdm": "null",
        "origem": "PortoNet",
        "ticket_sis_ext": "null"
    }
]